LICENSE
llama_hub/README.md
llama_hub/__init__.py
llama_hub/add_loader.sh
llama_hub/agent_search/README.md
llama_hub/agent_search/__init__.py
llama_hub/agent_search/base.py
llama_hub/agent_search/requirements.txt
llama_hub/airbyte_cdk/.gitignore
llama_hub/airbyte_cdk/README.md
llama_hub/airbyte_cdk/__init__.py
llama_hub/airbyte_cdk/base.py
llama_hub/airbyte_cdk/requirements.txt
llama_hub/airbyte_gong/README.md
llama_hub/airbyte_gong/__init__.py
llama_hub/airbyte_gong/base.py
llama_hub/airbyte_gong/requirements.txt
llama_hub/airbyte_hubspot/README.md
llama_hub/airbyte_hubspot/__init__.py
llama_hub/airbyte_hubspot/base.py
llama_hub/airbyte_hubspot/requirements.txt
llama_hub/airbyte_salesforce/README.md
llama_hub/airbyte_salesforce/__init__.py
llama_hub/airbyte_salesforce/base.py
llama_hub/airbyte_salesforce/requirements.txt
llama_hub/airbyte_shopify/README.md
llama_hub/airbyte_shopify/__init__.py
llama_hub/airbyte_shopify/base.py
llama_hub/airbyte_shopify/requirements.txt
llama_hub/airbyte_stripe/README.md
llama_hub/airbyte_stripe/__init__.py
llama_hub/airbyte_stripe/base.py
llama_hub/airbyte_stripe/requirements.txt
llama_hub/airbyte_typeform/README.md
llama_hub/airbyte_typeform/__init__.py
llama_hub/airbyte_typeform/base.py
llama_hub/airbyte_typeform/requirements.txt
llama_hub/airbyte_zendesk_support/README.md
llama_hub/airbyte_zendesk_support/__init__.py
llama_hub/airbyte_zendesk_support/base.py
llama_hub/airbyte_zendesk_support/requirements.txt
llama_hub/airtable/README.md
llama_hub/airtable/__init__.py
llama_hub/airtable/base.py
llama_hub/airtable/requirements.txt
llama_hub/apify/actor/README.md
llama_hub/apify/actor/__init__.py
llama_hub/apify/actor/base.py
llama_hub/apify/actor/requirements.txt
llama_hub/apify/dataset/README.md
llama_hub/apify/dataset/__init__.py
llama_hub/apify/dataset/base.py
llama_hub/apify/dataset/requirements.txt
llama_hub/asana/README.md
llama_hub/asana/__init__.py
llama_hub/asana/base.py
llama_hub/asana/requirements.txt
llama_hub-0.0.74.dist-info/LICENSE
llama_hub-0.0.74.dist-info/METADATA
llama_hub-0.0.74.dist-info/WHEEL
llama_hub-0.0.74.dist-info/RECORD
