Metadata-Version: 2.1
Name: llama-hub
Version: 0.0.74
Summary: A library of community-driven data loaders for LLMs. Use with LlamaIndex and/or LangChain. 
Home-page: https://llamahub.ai
License: MIT
Keywords: llama-index,llama-hub,llama
Author: Jerry Liu
Requires-Python: >=3.8.1,<3.12
Classifier: License :: OSI Approved :: MIT License
Classifier: Programming Language :: Python :: 3
Classifier: Programming Language :: Python :: 3.9
Classifier: Programming Language :: Python :: 3.10
Classifier: Programming Language :: Python :: 3.11
Requires-Dist: html2text
Requires-Dist: llama-index (>=0.9.29)
Requires-Dist: psutil
Requires-Dist: pyaml (>=23.9.7,<24.0.0)
Requires-Dist: retrying
Project-URL: Repository, https://github.com/emptycrown/llama-hub
